vega/__init__.py
vega/data/__init__.py
vega/data/_pbmc_ifn.py
vega/data/reactomes.gmt
vega/layers.py
vega/learning_utils.py
vega/plotting.py
vega/regularizers.py
vega/utils.py
vega/vega_count/__init__.py
vega/vega_count/_vegamodel.py
vega/vega_count/_vegamodule.py
vega/vega_model.py
scvega-0.0.2.dist-info/LICENSE
scvega-0.0.2.dist-info/WHEEL
scvega-0.0.2.dist-info/METADATA
scvega-0.0.2.dist-info/RECORD
